sentry_riak/__init__.py
sentry_riak/backend.py
sentry_riak/client.py
sentry_riak_node_storage-0.0.1.dist-info/METADATA
sentry_riak_node_storage-0.0.1.dist-info/WHEEL
sentry_riak_node_storage-0.0.1.dist-info/top_level.txt
sentry_riak_node_storage-0.0.1.dist-info/RECORD
